[{"model": "POI.category", "pk": 13, "fields": {"name": "by interaction", "parent": null, "lft": 1, "rght": 6, "tree_id": 1, "level": 0}}, {"model": "POI.category", "pk": 14, "fields": {"name": "active (visit or take part in)", "parent": 13, "lft": 2, "rght": 3, "tree_id": 1, "level": 1}}, {"model": "POI.category", "pk": 15, "fields": {"name": "pasive (just look)", "parent": 13, "lft": 4, "rght": 5, "tree_id": 1, "level": 1}}, {"model": "POI.category", "pk": 16, "fields": {"name": "by type", "parent": null, "lft": 1, "rght": 34, "tree_id": 2, "level": 0}}, {"model": "POI.category", "pk": 17, "fields": {"name": "art and culture", "parent": 16, "lft": 2, "rght": 13, "tree_id": 2, "level": 1}}, {"model": "POI.category", "pk": 18, "fields": {"name": "have fun or eating", "parent": 16, "lft": 20, "rght": 27, "tree_id": 2, "level": 1}}, {"model": "POI.category", "pk": 19, "fields": {"name": "religion", "parent": 16, "lft": 28, "rght": 33, "tree_id": 2, "level": 1}}, {"model": "POI.category", "pk": 20, "fields": {"name": "beautiful places", "parent": 16, "lft": 14, "rght": 19, "tree_id": 2, "level": 1}}, {"model": "POI.category", "pk": 21, "fields": {"name": "mass culture", "parent": 17, "lft": 11, "rght": 12, "tree_id": 2, "level": 2}}, {"model": "POI.category", "pk": 22, "fields": {"name": "historical places", "parent": 17, "lft": 9, "rght": 10, "tree_id": 2, "level": 2}}, {"model": "POI.category", "pk": 23, "fields": {"name": "cultural heritage", "parent": 17, "lft": 7, "rght": 8, "tree_id": 2, "level": 2}}, {"model": "POI.category", "pk": 24, "fields": {"name": "architecture", "parent": 17, "lft": 3, "rght": 4, "tree_id": 2, "level": 2}}, {"model": "POI.category", "pk": 25, "fields": {"name": "art", "parent": 17, "lft": 5, "rght": 6, "tree_id": 2, "level": 2}}, {"model": "POI.category", "pk": 26, "fields": {"name": "cinema", "parent": 18, "lft": 23, "rght": 24, "tree_id": 2, "level": 2}}, {"model": "POI.category", "pk": 27, "fields": {"name": "cafe, rerestaurant, pub", "parent": 18, "lft": 21, "rght": 22, "tree_id": 2, "level": 2}}, {"model": "POI.category", "pk": 28, "fields": {"name": "recreation", "parent": 18, "lft": 25, "rght": 26, "tree_id": 2, "level": 2}}, {"model": "POI.category", "pk": 31, "fields": {"name": "landscape", "parent": 20, "lft": 15, "rght": 16, "tree_id": 2, "level": 2}}, {"model": "POI.category", "pk": 32, "fields": {"name": "place", "parent": 20, "lft": 17, "rght": 18, "tree_id": 2, "level": 2}}, {"model": "POI.category", "pk": 33, "fields": {"name": "temples and churches", "parent": 19, "lft": 31, "rght": 32, "tree_id": 2, "level": 2}}, {"model": "POI.category", "pk": 34, "fields": {"name": "places of religious worship", "parent": 19, "lft": 29, "rght": 30, "tree_id": 2, "level": 2}}]